gui/__init__.py
gui/clipboard.py
gui/component.py
gui/dialog.py
gui/event.py
gui/flowsizer.py
gui/font.py
gui/graphic.py
gui/images.py
gui/menu.py
gui/registry.py
gui/resource.py
gui/spec.py
gui/statusbar.py
gui/timer.py
gui/util.py
gui/controls/__init__.py
gui/controls/button.py
gui/controls/canvas.py
gui/controls/checkbox.py
gui/controls/combobox.py
gui/controls/gauge.py
gui/controls/gridview.py
gui/controls/htmlbox.py
gui/controls/image.py
gui/controls/label.py
gui/controls/line.py
gui/controls/listbox.py
gui/controls/listview.py
gui/controls/notebook.py
gui/controls/panel.py
gui/controls/radiobutton.py
gui/controls/slider.py
gui/controls/textbox.py
gui/controls/treeview.py
gui/html/__init__.py
gui/html/form.py
gui/html/input.py
gui/html/label.py
gui/html/object.py
gui/html/select.py
gui/tools/__init__.py
gui/tools/debug.py
gui/tools/designer.py
gui/tools/inspector.py
gui/tools/migrate.py
gui/tools/propeditor.py
gui/tools/toolbox.py
gui/windows/__init__.py
gui/windows/htmlwin.py
gui/windows/window.py
gui2py-0.9.6.1.dist-info/DESCRIPTION.rst
gui2py-0.9.6.1.dist-info/METADATA
gui2py-0.9.6.1.dist-info/RECORD
gui2py-0.9.6.1.dist-info/WHEEL
gui2py-0.9.6.1.dist-info/metadata.json
gui2py-0.9.6.1.dist-info/top_level.txt
